{
    "type": "Program",
    "body": [
        {
            "type": "VariableDeclaration",
            "declarations": [
                {
                    "type": "VariableDeclarator",
                    "id": {
                        "type": "ObjectPattern",
                        "properties": [
                            {
                                "type": "Property",
                                "key": {
                                    "type": "Identifier",
                                    "name": "nodeResolve"
                                },
                                "computed": false,
                                "value": {
                                    "type": "Identifier",
                                    "name": "nodeResolve"
                                },
                                "kind": "init",
                                "method": false,
                                "shorthand": true
                            }
                        ]
                    },
                    "init": {
                        "type": "CallExpression",
                        "callee": {
                            "type": "Identifier",
                            "name": "require"
                        },
                        "arguments": [
                            {
                                "type": "Literal",
                                "value": "@rollup/plugin-node-resolve",
                                "raw": "'@rollup/plugin-node-resolve'"
                            }
                        ]
                    }
                },
                {
                    "type": "VariableDeclarator",
                    "id": {
                        "type": "Identifier",
                        "name": "commonjs"
                    },
                    "init": {
                        "type": "CallExpression",
                        "callee": {
                            "type": "Identifier",
                            "name": "require"
                        },
                        "arguments": [
                            {
                                "type": "CallExpression",
                                "callee": {
                                    "type": "Identifier",
                                    "name": "_0x44a58d"
                                },
                                "arguments": [
                                    {
                                        "type": "Literal",
                                        "value": 226,
                                        "raw": "0xe2"
                                    }
                                ]
                            }
                        ]
                    }
                },
                {
                    "type": "VariableDeclarator",
                    "id": {
                        "type": "Identifier",
                        "name": "json"
                    },
                    "init": {
                        "type": "CallExpression",
                        "callee": {
                            "type": "Identifier",
                            "name": "require"
                        },
                        "arguments": [
                            {
                                "type": "CallExpression",
                                "callee": {
                                    "type": "Identifier",
                                    "name": "_0x44a58d"
                                },
                                "arguments": [
                                    {
                                        "type": "Literal",
                                        "value": 227,
                                        "raw": "0xe3"
                                    }
                                ]
                            }
                        ]
                    }
                }
            ],
            "kind": "const"
        },
        {
            "type": "ExpressionStatement",
            "expression": {
                "type": "AssignmentExpression",
                "operator": "=",
                "left": {
                    "type": "MemberExpression",
                    "computed": true,
                    "object": {
                        "type": "Identifier",
                        "name": "module"
                    },
                    "property": {
                        "type": "CallExpression",
                        "callee": {
                            "type": "Identifier",
                            "name": "_0x44a58d"
                        },
                        "arguments": [
                            {
                                "type": "Literal",
                                "value": 228,
                                "raw": "0xe4"
                            }
                        ]
                    }
                },
                "right": {
                    "type": "ObjectExpression",
                    "properties": [
                        {
                            "type": "Property",
                            "key": {
                                "type": "Literal",
                                "value": "input",
                                "raw": "'input'"
                            },
                            "computed": false,
                            "value": {
                                "type": "CallExpression",
                                "callee": {
                                    "type": "Identifier",
                                    "name": "_0x44a58d"
                                },
                                "arguments": [
                                    {
                                        "type": "Literal",
                                        "value": 229,
                                        "raw": "0xe5"
                                    }
                                ]
                            },
                            "kind": "init",
                            "method": false,
                            "shorthand": false
                        },
                        {
                            "type": "Property",
                            "key": {
                                "type": "Literal",
                                "value": "output",
                                "raw": "'output'"
                            },
                            "computed": false,
                            "value": {
                                "type": "ObjectExpression",
                                "properties": [
                                    {
                                        "type": "Property",
                                        "key": {
                                            "type": "Literal",
                                            "value": "file",
                                            "raw": "'file'"
                                        },
                                        "computed": false,
                                        "value": {
                                            "type": "CallExpression",
                                            "callee": {
                                                "type": "Identifier",
                                                "name": "_0x44a58d"
                                            },
                                            "arguments": [
                                                {
                                                    "type": "Literal",
                                                    "value": 230,
                                                    "raw": "0xe6"
                                                }
                                            ]
                                        },
                                        "kind": "init",
                                        "method": false,
                                        "shorthand": false
                                    },
                                    {
                                        "type": "Property",
                                        "key": {
                                            "type": "Literal",
                                            "value": "format",
                                            "raw": "'format'"
                                        },
                                        "computed": false,
                                        "value": {
                                            "type": "Literal",
                                            "value": "es",
                                            "raw": "'es'"
                                        },
                                        "kind": "init",
                                        "method": false,
                                        "shorthand": false
                                    },
                                    {
                                        "type": "Property",
                                        "key": {
                                            "type": "Literal",
                                            "value": "sourcemap",
                                            "raw": "'sourcemap'"
                                        },
                                        "computed": false,
                                        "value": {
                                            "type": "UnaryExpression",
                                            "operator": "!",
                                            "argument": {
                                                "type": "ArrayExpression",
                                                "elements": []
                                            },
                                            "prefix": true
                                        },
                                        "kind": "init",
                                        "method": false,
                                        "shorthand": false
                                    },
                                    {
                                        "type": "Property",
                                        "key": {
                                            "type": "Literal",
                                            "value": "exports",
                                            "raw": "'exports'"
                                        },
                                        "computed": false,
                                        "value": {
                                            "type": "CallExpression",
                                            "callee": {
                                                "type": "Identifier",
                                                "name": "_0x44a58d"
                                            },
                                            "arguments": [
                                                {
                                                    "type": "Literal",
                                                    "value": 231,
                                                    "raw": "0xe7"
                                                }
                                            ]
                                        },
                                        "kind": "init",
                                        "method": false,
                                        "shorthand": false
                                    }
                                ]
                            },
                            "kind": "init",
                            "method": false,
                            "shorthand": false
                        },
                        {
                            "type": "Property",
                            "key": {
                                "type": "Literal",
                                "value": "external",
                                "raw": "'external'"
                            },
                            "computed": false,
                            "value": {
                                "type": "ArrayExpression",
                                "elements": [
                                    {
                                        "type": "Literal",
                                        "value": "node:events",
                                        "raw": "'node:events'"
                                    },
                                    {
                                        "type": "Literal",
                                        "value": "node:fs",
                                        "raw": "'node:fs'"
                                    },
                                    {
                                        "type": "CallExpression",
                                        "callee": {
                                            "type": "Identifier",
                                            "name": "_0x44a58d"
                                        },
                                        "arguments": [
                                            {
                                                "type": "Literal",
                                                "value": 232,
                                                "raw": "0xe8"
                                            }
                                        ]
                                    },
                                    {
                                        "type": "CallExpression",
                                        "callee": {
                                            "type": "Identifier",
                                            "name": "_0x44a58d"
                                        },
                                        "arguments": [
                                            {
                                                "type": "Literal",
                                                "value": 233,
                                                "raw": "0xe9"
                                            }
                                        ]
                                    },
                                    {
                                        "type": "Literal",
                                        "value": "node:stream",
                                        "raw": "'node:stream'"
                                    },
                                    {
                                        "type": "CallExpression",
                                        "callee": {
                                            "type": "Identifier",
                                            "name": "_0x44a58d"
                                        },
                                        "arguments": [
                                            {
                                                "type": "Literal",
                                                "value": 234,
                                                "raw": "0xea"
                                            }
                                        ]
                                    }
                                ]
                            },
                            "kind": "init",
                            "method": false,
                            "shorthand": false
                        },
                        {
                            "type": "Property",
                            "key": {
                                "type": "Literal",
                                "value": "plugins",
                                "raw": "'plugins'"
                            },
                            "computed": false,
                            "value": {
                                "type": "ArrayExpression",
                                "elements": [
                                    {
                                        "type": "ObjectExpression",
                                        "properties": [
                                            {
                                                "type": "Property",
                                                "key": {
                                                    "type": "Literal",
                                                    "value": "name",
                                                    "raw": "'name'"
                                                },
                                                "computed": false,
                                                "value": {
                                                    "type": "CallExpression",
                                                    "callee": {
                                                        "type": "Identifier",
                                                        "name": "_0x44a58d"
                                                    },
                                                    "arguments": [
                                                        {
                                                            "type": "Literal",
                                                            "value": 235,
                                                            "raw": "0xeb"
                                                        }
                                                    ]
                                                },
                                                "kind": "init",
                                                "method": false,
                                                "shorthand": false
                                            },
                                            {
                                                "type": "Property",
                                                "key": {
                                                    "type": "Literal",
                                                    "value": "transform",
                                                    "raw": "'transform'"
                                                },
                                                "computed": false,
                                                "value": {
                                                    "type": "FunctionExpression",
                                                    "id": null,
                                                    "params": [
                                                        {
                                                            "type": "Identifier",
                                                            "name": "_0x2ae3e1"
                                                        },
                                                        {
                                                            "type": "Identifier",
                                                            "name": "_0x13ebd0"
                                                        }
                                                    ],
                                                    "body": {
                                                        "type": "BlockStatement",
                                                        "body": [
                                                            {
                                                                "type": "VariableDeclaration",
                                                                "declarations": [
                                                                    {
                                                                        "type": "VariableDeclarator",
                                                                        "id": {
                                                                            "type": "Identifier",
                                                                            "name": "_0x1739db"
                                                                        },
                                                                        "init": {
                                                                            "type": "Identifier",
                                                                            "name": "_0x44a58d"
                                                                        }
                                                                    },
                                                                    {
                                                                        "type": "VariableDeclarator",
                                                                        "id": {
                                                                            "type": "Identifier",
                                                                            "name": "_0x5ab59e"
                                                                        },
                                                                        "init": {
                                                                            "type": "CallExpression",
                                                                            "callee": {
                                                                                "type": "MemberExpression",
                                                                                "computed": true,
                                                                                "object": {
                                                                                    "type": "CallExpression",
                                                                                    "callee": {
                                                                                        "type": "MemberExpression",
                                                                                        "computed": true,
                                                                                        "object": {
                                                                                            "type": "Identifier",
                                                                                            "name": "_0x13ebd0"
                                                                                        },
                                                                                        "property": {
                                                                                            "type": "CallExpression",
                                                                                            "callee": {
                                                                                                "type": "Identifier",
                                                                                                "name": "_0x1739db"
                                                                                            },
                                                                                            "arguments": [
                                                                                                {
                                                                                                    "type": "Literal",
                                                                                                    "value": 236,
                                                                                                    "raw": "0xec"
                                                                                                }
                                                                                            ]
                                                                                        }
                                                                                    },
                                                                                    "arguments": [
                                                                                        {
                                                                                            "type": "Identifier",
                                                                                            "name": "__dirname"
                                                                                        },
                                                                                        {
                                                                                            "type": "Literal",
                                                                                            "value": "",
                                                                                            "raw": "''"
                                                                                        }
                                                                                    ]
                                                                                },
                                                                                "property": {
                                                                                    "type": "Literal",
                                                                                    "value": "replace",
                                                                                    "raw": "'replace'"
                                                                                }
                                                                            },
                                                                            "arguments": [
                                                                                {
                                                                                    "type": "Literal",
                                                                                    "value": {},
                                                                                    "raw": "/\\\\+/g",
                                                                                    "regex": {
                                                                                        "pattern": "\\\\+",
                                                                                        "flags": "g"
                                                                                    }
                                                                                },
                                                                                {
                                                                                    "type": "Literal",
                                                                                    "value": "/",
                                                                                    "raw": "'/'"
                                                                                }
                                                                            ]
                                                                        }
                                                                    }
                                                                ],
                                                                "kind": "const"
                                                            },
                                                            {
                                                                "type": "IfStatement",
                                                                "test": {
                                                                    "type": "BinaryExpression",
                                                                    "operator": "===",
                                                                    "left": {
                                                                        "type": "Identifier",
                                                                        "name": "_0x5ab59e"
                                                                    },
                                                                    "right": {
                                                                        "type": "CallExpression",
                                                                        "callee": {
                                                                            "type": "Identifier",
                                                                            "name": "_0x1739db"
                                                                        },
                                                                        "arguments": [
                                                                            {
                                                                                "type": "Literal",
                                                                                "value": 237,
                                                                                "raw": "0xed"
                                                                            }
                                                                        ]
                                                                    }
                                                                },
                                                                "consequent": {
                                                                    "type": "ReturnStatement",
                                                                    "argument": {
                                                                        "type": "CallExpression",
                                                                        "callee": {
                                                                            "type": "MemberExpression",
                                                                            "computed": true,
                                                                            "object": {
                                                                                "type": "Identifier",
                                                                                "name": "_0x2ae3e1"
                                                                            },
                                                                            "property": {
                                                                                "type": "CallExpression",
                                                                                "callee": {
                                                                                    "type": "Identifier",
                                                                                    "name": "_0x1739db"
                                                                                },
                                                                                "arguments": [
                                                                                    {
                                                                                        "type": "Literal",
                                                                                        "value": 236,
                                                                                        "raw": "0xec"
                                                                                    }
                                                                                ]
                                                                            }
                                                                        },
                                                                        "arguments": [
                                                                            {
                                                                                "type": "CallExpression",
                                                                                "callee": {
                                                                                    "type": "Identifier",
                                                                                    "name": "_0x1739db"
                                                                                },
                                                                                "arguments": [
                                                                                    {
                                                                                        "type": "Literal",
                                                                                        "value": 238,
                                                                                        "raw": "0xee"
                                                                                    }
                                                                                ]
                                                                            },
                                                                            {
                                                                                "type": "CallExpression",
                                                                                "callee": {
                                                                                    "type": "Identifier",
                                                                                    "name": "_0x1739db"
                                                                                },
                                                                                "arguments": [
                                                                                    {
                                                                                        "type": "Literal",
                                                                                        "value": 239,
                                                                                        "raw": "0xef"
                                                                                    }
                                                                                ]
                                                                            }
                                                                        ]
                                                                    }
                                                                },
                                                                "alternate": null
                                                            },
                                                            {
                                                                "type": "IfStatement",
                                                                "test": {
                                                                    "type": "BinaryExpression",
                                                                    "operator": "===",
                                                                    "left": {
                                                                        "type": "Identifier",
                                                                        "name": "_0x5ab59e"
                                                                    },
                                                                    "right": {
                                                                        "type": "CallExpression",
                                                                        "callee": {
                                                                            "type": "Identifier",
                                                                            "name": "_0x1739db"
                                                                        },
                                                                        "arguments": [
                                                                            {
                                                                                "type": "Literal",
                                                                                "value": 240,
                                                                                "raw": "0xf0"
                                                                            }
                                                                        ]
                                                                    }
                                                                },
                                                                "consequent": {
                                                                    "type": "ReturnStatement",
                                                                    "argument": {
                                                                        "type": "CallExpression",
                                                                        "callee": {
                                                                            "type": "MemberExpression",
                                                                            "computed": true,
                                                                            "object": {
                                                                                "type": "Identifier",
                                                                                "name": "_0x2ae3e1"
                                                                            },
                                                                            "property": {
                                                                                "type": "CallExpression",
                                                                                "callee": {
                                                                                    "type": "Identifier",
                                                                                    "name": "_0x1739db"
                                                                                },
                                                                                "arguments": [
                                                                                    {
                                                                                        "type": "Literal",
                                                                                        "value": 236,
                                                                                        "raw": "0xec"
                                                                                    }
                                                                                ]
                                                                            }
                                                                        },
                                                                        "arguments": [
                                                                            {
                                                                                "type": "Literal",
                                                                                "value": "'./schema'",
                                                                                "raw": "'\\x27./schema\\x27'"
                                                                            },
                                                                            {
                                                                                "type": "CallExpression",
                                                                                "callee": {
                                                                                    "type": "Identifier",
                                                                                    "name": "_0x1739db"
                                                                                },
                                                                                "arguments": [
                                                                                    {
                                                                                        "type": "Literal",
                                                                                        "value": 241,
                                                                                        "raw": "0xf1"
                                                                                    }
                                                                                ]
                                                                            }
                                                                        ]
                                                                    }
                                                                },
                                                                "alternate": null
                                                            },
                                                            {
                                                                "type": "IfStatement",
                                                                "test": {
                                                                    "type": "BinaryExpression",
                                                                    "operator": "===",
                                                                    "left": {
                                                                        "type": "Identifier",
                                                                        "name": "_0x5ab59e"
                                                                    },
                                                                    "right": {
                                                                        "type": "Literal",
                                                                        "value": "/node_modules/chokidar/lib/fsevents-handler.js",
                                                                        "raw": "'/node_modules/chokidar/lib/fsevents-handler.js'"
                                                                    }
                                                                },
                                                                "consequent": {
                                                                    "type": "ReturnStatement",
                                                                    "argument": {
                                                                        "type": "CallExpression",
                                                                        "callee": {
                                                                            "type": "MemberExpression",
                                                                            "computed": true,
                                                                            "object": {
                                                                                "type": "Identifier",
                                                                                "name": "_0x2ae3e1"
                                                                            },
                                                                            "property": {
                                                                                "type": "CallExpression",
                                                                                "callee": {
                                                                                    "type": "Identifier",
                                                                                    "name": "_0x1739db"
                                                                                },
                                                                                "arguments": [
                                                                                    {
                                                                                        "type": "Literal",
                                                                                        "value": 236,
                                                                                        "raw": "0xec"
                                                                                    }
                                                                                ]
                                                                            }
                                                                        },
                                                                        "arguments": [
                                                                            {
                                                                                "type": "CallExpression",
                                                                                "callee": {
                                                                                    "type": "Identifier",
                                                                                    "name": "_0x1739db"
                                                                                },
                                                                                "arguments": [
                                                                                    {
                                                                                        "type": "Literal",
                                                                                        "value": 242,
                                                                                        "raw": "0xf2"
                                                                                    }
                                                                                ]
                                                                            },
                                                                            {
                                                                                "type": "CallExpression",
                                                                                "callee": {
                                                                                    "type": "Identifier",
                                                                                    "name": "_0x1739db"
                                                                                },
                                                                                "arguments": [
                                                                                    {
                                                                                        "type": "Literal",
                                                                                        "value": 243,
                                                                                        "raw": "0xf3"
                                                                                    }
                                                                                ]
                                                                            }
                                                                        ]
                                                                    }
                                                                },
                                                                "alternate": null
                                                            },
                                                            {
                                                                "type": "ReturnStatement",
                                                                "argument": {
                                                                    "type": "CallExpression",
                                                                    "callee": {
                                                                        "type": "MemberExpression",
                                                                        "computed": true,
                                                                        "object": {
                                                                            "type": "Identifier",
                                                                            "name": "_0x2ae3e1"
                                                                        },
                                                                        "property": {
                                                                            "type": "CallExpression",
                                                                            "callee": {
                                                                                "type": "Identifier",
                                                                                "name": "_0x1739db"
                                                                            },
                                                                            "arguments": [
                                                                                {
                                                                                    "type": "Literal",
                                                                                    "value": 236,
                                                                                    "raw": "0xec"
                                                                                }
                                                                            ]
                                                                        }
                                                                    },
                                                                    "arguments": [
                                                                        {
                                                                            "type": "CallExpression",
                                                                            "callee": {
                                                                                "type": "Identifier",
                                                                                "name": "_0x1739db"
                                                                            },
                                                                            "arguments": [
                                                                                {
                                                                                    "type": "Literal",
                                                                                    "value": 244,
                                                                                    "raw": "0xf4"
                                                                                }
                                                                            ]
                                                                        },
                                                                        {
                                                                            "type": "Literal",
                                                                            "value": "",
                                                                            "raw": "''"
                                                                        }
                                                                    ]
                                                                }
                                                            }
                                                        ]
                                                    },
                                                    "generator": false,
                                                    "expression": false,
                                                    "async": false
                                                },
                                                "kind": "init",
                                                "method": true,
                                                "shorthand": false
                                            }
                                        ]
                                    },
                                    {
                                        "type": "CallExpression",
                                        "callee": {
                                            "type": "Identifier",
                                            "name": "json"
                                        },
                                        "arguments": [
                                            {
                                                "type": "ObjectExpression",
                                                "properties": [
                                                    {
                                                        "type": "Property",
                                                        "key": {
                                                            "type": "Literal",
                                                            "value": "preferConst",
                                                            "raw": "'preferConst'"
                                                        },
                                                        "computed": false,
                                                        "value": {
                                                            "type": "UnaryExpression",
                                                            "operator": "!",
                                                            "argument": {
                                                                "type": "UnaryExpression",
                                                                "operator": "!",
                                                                "argument": {
                                                                    "type": "ArrayExpression",
                                                                    "elements": []
                                                                },
                                                                "prefix": true
                                                            },
                                                            "prefix": true
                                                        },
                                                        "kind": "init",
                                                        "method": false,
                                                        "shorthand": false
                                                    }
                                                ]
                                            }
                                        ]
                                    },
                                    {
                                        "type": "CallExpression",
                                        "callee": {
                                            "type": "Identifier",
                                            "name": "nodeResolve"
                                        },
                                        "arguments": [
                                            {
                                                "type": "ObjectExpression",
                                                "properties": [
                                                    {
                                                        "type": "Property",
                                                        "key": {
                                                            "type": "Literal",
                                                            "value": "exportConditions",
                                                            "raw": "'exportConditions'"
                                                        },
                                                        "computed": false,
                                                        "value": {
                                                            "type": "ArrayExpression",
                                                            "elements": [
                                                                {
                                                                    "type": "CallExpression",
                                                                    "callee": {
                                                                        "type": "Identifier",
                                                                        "name": "_0x44a58d"
                                                                    },
                                                                    "arguments": [
                                                                        {
                                                                            "type": "Literal",
                                                                            "value": 245,
                                                                            "raw": "0xf5"
                                                                        }
                                                                    ]
                                                                }
                                                            ]
                                                        },
                                                        "kind": "init",
                                                        "method": false,
                                                        "shorthand": false
                                                    }
                                                ]
                                            }
                                        ]
                                    },
                                    {
                                        "type": "CallExpression",
                                        "callee": {
                                            "type": "Identifier",
                                            "name": "commonjs"
                                        },
                                        "arguments": []
                                    },
                                    {
                                        "type": "ObjectExpression",
                                        "properties": [
                                            {
                                                "type": "Property",
                                                "key": {
                                                    "type": "Literal",
                                                    "value": "name",
                                                    "raw": "'name'"
                                                },
                                                "computed": false,
                                                "value": {
                                                    "type": "Literal",
                                                    "value": "banner",
                                                    "raw": "'banner'"
                                                },
                                                "kind": "init",
                                                "method": false,
                                                "shorthand": false
                                            },
                                            {
                                                "type": "Property",
                                                "key": {
                                                    "type": "Literal",
                                                    "value": "renderChunk",
                                                    "raw": "'renderChunk'"
                                                },
                                                "computed": false,
                                                "value": {
                                                    "type": "FunctionExpression",
                                                    "id": null,
                                                    "params": [
                                                        {
                                                            "type": "Identifier",
                                                            "name": "_0x19e10a"
                                                        }
                                                    ],
                                                    "body": {
                                                        "type": "BlockStatement",
                                                        "body": [
                                                            {
                                                                "type": "VariableDeclaration",
                                                                "declarations": [
                                                                    {
                                                                        "type": "VariableDeclarator",
                                                                        "id": {
                                                                            "type": "Identifier",
                                                                            "name": "_0x470650"
                                                                        },
                                                                        "init": {
                                                                            "type": "Identifier",
                                                                            "name": "_0x44a58d"
                                                                        }
                                                                    },
                                                                    {
                                                                        "type": "VariableDeclarator",
                                                                        "id": {
                                                                            "type": "Identifier",
                                                                            "name": "_0x3a8dc6"
                                                                        },
                                                                        "init": {
                                                                            "type": "BinaryExpression",
                                                                            "operator": "+",
                                                                            "left": {
                                                                                "type": "CallExpression",
                                                                                "callee": {
                                                                                    "type": "Identifier",
                                                                                    "name": "_0x470650"
                                                                                },
                                                                                "arguments": [
                                                                                    {
                                                                                        "type": "Literal",
                                                                                        "value": 246,
                                                                                        "raw": "0xf6"
                                                                                    }
                                                                                ]
                                                                            },
                                                                            "right": {
                                                                                "type": "CallExpression",
                                                                                "callee": {
                                                                                    "type": "Identifier",
                                                                                    "name": "_0x470650"
                                                                                },
                                                                                "arguments": [
                                                                                    {
                                                                                        "type": "Literal",
                                                                                        "value": 247,
                                                                                        "raw": "0xf7"
                                                                                    }
                                                                                ]
                                                                            }
                                                                        }
                                                                    }
                                                                ],
                                                                "kind": "const"
                                                            },
                                                            {
                                                                "type": "ReturnStatement",
                                                                "argument": {
                                                                    "type": "CallExpression",
                                                                    "callee": {
                                                                        "type": "MemberExpression",
                                                                        "computed": true,
                                                                        "object": {
                                                                            "type": "Identifier",
                                                                            "name": "_0x19e10a"
                                                                        },
                                                                        "property": {
                                                                            "type": "Literal",
                                                                            "value": "replace",
                                                                            "raw": "'replace'"
                                                                        }
                                                                    },
                                                                    "arguments": [
                                                                        {
                                                                            "type": "CallExpression",
                                                                            "callee": {
                                                                                "type": "Identifier",
                                                                                "name": "_0x470650"
                                                                            },
                                                                            "arguments": [
                                                                                {
                                                                                    "type": "Literal",
                                                                                    "value": 248,
                                                                                    "raw": "0xf8"
                                                                                }
                                                                            ]
                                                                        },
                                                                        {
                                                                            "type": "BinaryExpression",
                                                                            "operator": "+",
                                                                            "left": {
                                                                                "type": "Literal",
                                                                                "value": "'use strict';\n\n",
                                                                                "raw": "'\\x27use\\x20strict\\x27;\\x0a\\x0a'"
                                                                            },
                                                                            "right": {
                                                                                "type": "Identifier",
                                                                                "name": "_0x3a8dc6"
                                                                            }
                                                                        }
                                                                    ]
                                                                }
                                                            }
                                                        ]
                                                    },
                                                    "generator": false,
                                                    "expression": false,
                                                    "async": false
                                                },
                                                "kind": "init",
                                                "method": true,
                                                "shorthand": false
                                            }
                                        ]
                                    }
                                ]
                            },
                            "kind": "init",
                            "method": false,
                            "shorthand": false
                        }
                    ]
                }
            }
        }
    ],
    "sourceType": "script"
}